krillscan/__init__.py
krillscan/inspect.py
krillscan/process.py
krillscan/echolab2/__init__.py
krillscan/echolab2/ping_data.py
krillscan/echolab2/instruments/EK60.py
krillscan/echolab2/instruments/EK80.py
krillscan/echolab2/instruments/__init__.py
krillscan/echolab2/instruments/echosounder.py
krillscan/echolab2/instruments/util/__init__.py
krillscan/echolab2/instruments/util/annotation_data.py
krillscan/echolab2/instruments/util/bottom_data.py
krillscan/echolab2/instruments/util/date_conversion.py
krillscan/echolab2/instruments/util/ek80_datagram_example.py
krillscan/echolab2/instruments/util/motion_data.py
krillscan/echolab2/instruments/util/nmea_data.py
krillscan/echolab2/instruments/util/read_idx_example.py
krillscan/echolab2/instruments/util/simrad_calibration.py
krillscan/echolab2/instruments/util/simrad_parsers.py
krillscan/echolab2/instruments/util/simrad_raw_file.py
krillscan/echolab2/instruments/util/simrad_signal_proc.py
krillscan/echolab2/instruments/util/pynmea2/__init__.py
krillscan/echolab2/instruments/util/pynmea2/_version.py
krillscan/echolab2/instruments/util/pynmea2/nmea.py
krillscan/echolab2/instruments/util/pynmea2/nmea_file.py
krillscan/echolab2/instruments/util/pynmea2/nmea_utils.py
krillscan/echolab2/instruments/util/pynmea2/seatalk_utils.py
krillscan/echolab2/instruments/util/pynmea2/stream.py
krillscan/echolab2/instruments/util/pynmea2/types/__init__.py
krillscan/echolab2/instruments/util/pynmea2/types/talker.py
krillscan/echolab2/instruments/util/pynmea2/types/proprietary/__init__.py
krillscan/echolab2/instruments/util/pynmea2/types/proprietary/ash.py
krillscan/echolab2/instruments/util/pynmea2/types/proprietary/grm.py
krillscan/echolab2/instruments/util/pynmea2/types/proprietary/rdi.py
krillscan/echolab2/instruments/util/pynmea2/types/proprietary/srf.py
krillscan/echolab2/instruments/util/pynmea2/types/proprietary/sxn.py
krillscan/echolab2/instruments/util/pynmea2/types/proprietary/tnl.py
krillscan-0.3.1.dist-info/METADATA
krillscan-0.3.1.dist-info/WHEEL
krillscan-0.3.1.dist-info/top_level.txt
krillscan-0.3.1.dist-info/RECORD
