Metadata-Version: 2.1
Name: krillscan
Version: 0.3.1
Summary: A python module for automatic analysis of backscatter data from vessels of opportunity
Home-page: 
Author: Sebastian Menze
Author-email: sebastian.menze@gmail.com
Classifier: Programming Language :: Python :: 3.9
Requires-Dist: lxml
Requires-Dist: numpy
Requires-Dist: matplotlib
Requires-Dist: pandas
Requires-Dist: future
Requires-Dist: pyproj
Requires-Dist: scikit-image
Requires-Dist: scipy
Requires-Dist: toml
Requires-Dist: geopy
Requires-Dist: tables
Requires-Dist: xarray
Requires-Dist: netcdf4
Requires-Dist: pyqtdarktheme
